Metadata-Version: 1.1
Name: pyaop
Version: 0.0.4
Summary: proxy hook like aop. 
Home-page: https://www.github.com/ShichaoMa/pyaop
Author: cn
Author-email: cnaafhvk@foxmail.com
License: MIT
Keywords: aop proxy hook
Platform: UNKNOWN
Classifier: License :: OSI Approved :: MIT License
Classifier: Programming Language :: Python
Classifier: Intended Audience :: Developers
Classifier: Operating System :: OS Independent
